setup.cfg
setup.py
ticpy/__init__.py
ticpy.egg-info/PKG-INFO
ticpy.egg-info/SOURCES.txt
ticpy.egg-info/dependency_links.txt
ticpy.egg-info/entry_points.txt
ticpy.egg-info/not-zip-safe
ticpy.egg-info/requires.txt
ticpy.egg-info/top_level.txt
ticpy/src/__init__.py
ticpy/src/board.py
ticpy/src/cell.py
ticpy/src/constants.py
ticpy/src/game.py
ticpy/tests/__init__.py
ticpy/tests/conftest.py
ticpy/tests/test_board.py
ticpy/tests/test_cell.py
ticpy/tests/test_game.py