Metadata-Version: 1.1
Name: ticpy
Version: 0.3.1
Summary: ticpy
Home-page: https://github.com/rahul1990gupta/TicPy
Author: Rahul Gupta
Author-email: rahul1990gupta@gmail.com
License: UNKNOWN
Keywords: tic tac toe in python
Platform: UNKNOWN
Classifier: Programming Language :: Python
Classifier: Topic :: Internet :: WWW/HTTP
Classifier: Topic :: Internet :: WWW/HTTP :: WSGI :: Application
